stt_remote/__init__.py
stt_remote/transcriber.py
stt_remote-0.0.1.dist-info/LICENSE
stt_remote-0.0.1.dist-info/METADATA
stt_remote-0.0.1.dist-info/WHEEL
stt_remote-0.0.1.dist-info/top_level.txt
stt_remote-0.0.1.dist-info/RECORD
