Metadata-Version: 2.1
Name: stt-remote
Version: 0.0.1
Summary: Client package for hosted Coqui STT service
Home-page: https://github.com/coqui-ai/stt-remote
Author: Coqui GmbH
Author-email: info@coqui.ai
License: Apache License 2.0
Platform: UNKNOWN
Classifier: Development Status :: 3 - Alpha
Classifier: Intended Audience :: Developers
Classifier: Topic :: Multimedia :: Sound/Audio :: Speech
Classifier: License :: OSI Approved :: Apache Software License
Classifier: Programming Language :: Python :: 3
Requires-Python: <4,>=3.7
License-File: LICENSE
Requires-Dist: requests (==2.25.1)
Requires-Dist: tqdm (==4.64.0)
Requires-Dist: requests-futures (==1.0.0)
